stigrock/__init__.py
stigrock-1.2.0.dist-info/METADATA
stigrock-1.2.0.dist-info/WHEEL
stigrock-1.2.0.dist-info/top_level.txt
stigrock-1.2.0.dist-info/RECORD
