Metadata-Version: 2.4
Name: stigrock
Version: 1.2.0
Summary: Stigrock v1.2 - Progetto Python con contenuti web
Author-email: dnfhacktm <dnfhacktm@libero.it>
License-Expression: MIT
Project-URL: Homepage, https://github.com/dnfhacktm/stigrock-v1.2
Requires-Python: >=3.8
